micropub/__init__.py
micropub/__main__.py
micropub-0.1.3.dist-info/METADATA
micropub-0.1.3.dist-info/entry_points.txt
micropub-0.1.3.dist-info/WHEEL
micropub-0.1.3.dist-info/RECORD
